[{"timestamp":"2024-06-02T00:00:00.000Z","count":5,"uniques":1},{"timestamp":"2024-06-03T00:00:00.000Z","count":3,"uniques":1},{"timestamp":"2024-06-04T00:00:00.000Z","count":3,"uniques":1},{"timestamp":"2024-06-05T09:09:33.285Z","count":0,"uniques":0},{"timestamp":"2024-06-06T09:09:33.285Z","count":0,"uniques":0},{"timestamp":"2024-06-07T00:50:42.960Z","count":0,"uniques":0},{"timestamp":"2024-06-08T00:47:43.490Z","count":0,"uniques":0},{"timestamp":"2024-06-09T00:53:19.608Z","count":0,"uniques":0},{"timestamp":"2024-06-10T00:00:00.000Z","count":3,"uniques":1},{"timestamp":"2024-06-11T10:32:16.869Z","count":0,"uniques":0},{"timestamp":"2024-06-12T00:49:25.756Z","count":0,"uniques":0},{"timestamp":"2024-06-13T00:48:18.359Z","count":0,"uniques":0},{"timestamp":"2024-06-14T00:48:11.032Z","count":0,"uniques":0},{"timestamp":"2024-06-15T00:50:37.859Z","count":0,"uniques":0},{"timestamp":"2024-06-16T00:53:10.338Z","count":0,"uniques":0},{"timestamp":"2024-06-17T00:51:13.390Z","count":0,"uniques":0},{"timestamp":"2024-06-18T00:49:32.294Z","count":0,"uniques":0},{"timestamp":"2024-06-19T00:49:09.403Z","count":0,"uniques":0},{"timestamp":"2024-06-20T00:47:24.238Z","count":0,"uniques":0},{"timestamp":"2024-06-21T00:50:01.012Z","count":0,"uniques":0},{"timestamp":"2024-06-22T00:47:39.371Z","count":0,"uniques":0},{"timestamp":"2024-06-23T00:52:33.043Z","count":0,"uniques":0},{"timestamp":"2024-06-24T00:50:46.164Z","count":0,"uniques":0},{"timestamp":"2024-06-25T00:49:12.473Z","count":0,"uniques":0},{"timestamp":"2024-06-26T00:48:34.677Z","count":0,"uniques":0},{"timestamp":"2024-06-27T00:49:24.664Z","count":0,"uniques":0},{"timestamp":"2024-06-28T00:49:18.531Z","count":0,"uniques":0},{"timestamp":"2024-06-29T00:48:12.231Z","count":0,"uniques":0},{"timestamp":"2024-06-30T00:54:10.749Z","count":0,"uniques":0},{"timestamp":"2024-07-01T00:55:23.813Z","count":0,"uniques":0},{"timestamp":"2024-07-02T00:49:24.517Z","count":0,"uniques":0},{"timestamp":"2024-07-03T00:49:33.286Z","count":0,"uniques":0},{"timestamp":"2024-07-04T00:00:00.000Z","count":1,"uniques":1},{"timestamp":"2024-07-05T00:49:13.438Z","count":0,"uniques":0},{"timestamp":"2024-07-06T00:47:31.134Z","count":0,"uniques":0},{"timestamp":"2024-07-07T00:54:37.430Z","count":0,"uniques":0},{"timestamp":"2024-07-08T00:51:51.076Z","count":0,"uniques":0},{"timestamp":"2024-07-09T00:00:00.000Z","count":5,"uniques":1},{"timestamp":"2024-07-10T00:51:16.568Z","count":0,"uniques":0},{"timestamp":"2024-07-11T00:51:04.748Z","count":0,"uniques":0},{"timestamp":"2024-07-12T00:50:05.372Z","count":0,"uniques":0},{"timestamp":"2024-07-13T00:51:02.772Z","count":0,"uniques":0},{"timestamp":"2024-07-14T00:55:09.311Z","count":0,"uniques":0},{"timestamp":"2024-07-15T00:00:00.000Z","count":11,"uniques":1},{"timestamp":"2024-07-16T00:51:39.126Z","count":0,"uniques":0},{"timestamp":"2024-07-17T00:51:36.532Z","count":0,"uniques":0},{"timestamp":"2024-07-18T00:50:15.718Z","count":0,"uniques":0},{"timestamp":"2024-07-19T00:52:46.080Z","count":0,"uniques":0},{"timestamp":"2024-07-20T00:49:45.367Z","count":0,"uniques":0},{"timestamp":"2024-07-21T00:54:56.414Z","count":0,"uniques":0},{"timestamp":"2024-07-22T00:53:02.808Z","count":0,"uniques":0},{"timestamp":"2024-07-23T00:51:30.551Z","count":0,"uniques":0},{"timestamp":"2024-07-24T00:52:13.311Z","count":0,"uniques":0},{"timestamp":"2024-07-25T00:51:23.076Z","count":0,"uniques":0},{"timestamp":"2024-07-26T00:50:53.891Z","count":0,"uniques":0},{"timestamp":"2024-07-27T00:50:41.787Z","count":0,"uniques":0},{"timestamp":"2024-07-28T00:55:17.114Z","count":0,"uniques":0},{"timestamp":"2024-07-29T00:52:51.575Z","count":0,"uniques":0},{"timestamp":"2024-07-30T00:51:32.414Z","count":0,"uniques":0},{"timestamp":"2024-07-31T00:41:27.764Z","count":0,"uniques":0},{"timestamp":"2024-08-01T00:55:59.675Z","count":0,"uniques":0},{"timestamp":"2024-08-02T00:51:42.101Z","count":0,"uniques":0},{"timestamp":"2024-08-03T00:50:56.699Z","count":0,"uniques":0},{"timestamp":"2024-08-04T00:55:35.431Z","count":0,"uniques":0},{"timestamp":"2024-08-05T00:53:19.595Z","count":0,"uniques":0},{"timestamp":"2024-08-06T00:51:51.622Z","count":0,"uniques":0},{"timestamp":"2024-08-07T00:52:34.030Z","count":0,"uniques":0},{"timestamp":"2024-08-08T00:52:29.614Z","count":0,"uniques":0},{"timestamp":"2024-08-09T00:52:51.751Z","count":0,"uniques":0},{"timestamp":"2024-08-10T00:52:20.662Z","count":0,"uniques":0},{"timestamp":"2024-08-11T00:56:17.231Z","count":0,"uniques":0},{"timestamp":"2024-08-12T00:53:48.992Z","count":0,"uniques":0},{"timestamp":"2024-08-13T00:53:28.455Z","count":0,"uniques":0},{"timestamp":"2024-08-14T00:52:43.341Z","count":0,"uniques":0},{"timestamp":"2024-08-15T00:49:54.369Z","count":0,"uniques":0},{"timestamp":"2024-08-16T00:52:08.687Z","count":0,"uniques":0},{"timestamp":"2024-08-17T00:50:31.499Z","count":0,"uniques":0},{"timestamp":"2024-08-18T00:55:34.357Z","count":0,"uniques":0},{"timestamp":"2024-08-19T00:53:06.126Z","count":0,"uniques":0},{"timestamp":"2024-08-20T00:52:10.118Z","count":0,"uniques":0},{"timestamp":"2024-08-21T00:52:11.696Z","count":0,"uniques":0},{"timestamp":"2024-08-22T00:53:24.209Z","count":0,"uniques":0},{"timestamp":"2024-08-23T00:52:29.679Z","count":0,"uniques":0},{"timestamp":"2024-08-24T00:51:19.954Z","count":0,"uniques":0},{"timestamp":"2024-08-25T00:56:37.460Z","count":0,"uniques":0},{"timestamp":"2024-08-26T00:53:06.447Z","count":0,"uniques":0},{"timestamp":"2024-08-27T00:53:38.520Z","count":0,"uniques":0},{"timestamp":"2024-08-28T00:54:08.661Z","count":0,"uniques":0},{"timestamp":"2024-08-29T00:54:25.044Z","count":0,"uniques":0},{"timestamp":"2024-08-30T00:54:34.549Z","count":0,"uniques":0},{"timestamp":"2024-08-31T00:54:20.402Z","count":0,"uniques":0},{"timestamp":"2024-09-01T01:03:13.526Z","count":0,"uniques":0},{"timestamp":"2024-09-02T00:55:52.753Z","count":0,"uniques":0},{"timestamp":"2024-09-03T00:54:13.729Z","count":0,"uniques":0},{"timestamp":"2024-09-04T00:55:06.354Z","count":0,"uniques":0},{"timestamp":"2024-09-05T00:54:57.543Z","count":0,"uniques":0},{"timestamp":"2024-09-06T00:54:56.353Z","count":0,"uniques":0},{"timestamp":"2024-09-07T00:53:55.881Z","count":0,"uniques":0},{"timestamp":"2024-09-08T00:59:20.417Z","count":0,"uniques":0},{"timestamp":"2024-09-09T00:56:57.524Z","count":0,"uniques":0},{"timestamp":"2024-09-10T00:55:48.742Z","count":0,"uniques":0},{"timestamp":"2024-09-11T00:55:12.756Z","count":0,"uniques":0},{"timestamp":"2024-09-12T00:55:13.039Z","count":0,"uniques":0},{"timestamp":"2024-09-13T00:55:16.241Z","count":0,"uniques":0},{"timestamp":"2024-09-14T00:54:48.321Z","count":0,"uniques":0},{"timestamp":"2024-09-15T01:01:23.410Z","count":0,"uniques":0},{"timestamp":"2024-09-16T00:58:47.066Z","count":0,"uniques":0},{"timestamp":"2024-09-17T00:44:53.287Z","count":0,"uniques":0},{"timestamp":"2024-09-18T00:55:20.734Z","count":0,"uniques":0},{"timestamp":"2024-09-19T00:56:16.351Z","count":0,"uniques":0},{"timestamp":"2024-09-20T00:56:13.343Z","count":0,"uniques":0},{"timestamp":"2024-09-21T00:55:25.216Z","count":0,"uniques":0},{"timestamp":"2024-09-22T01:01:35.936Z","count":0,"uniques":0},{"timestamp":"2024-09-23T00:57:59.451Z","count":0,"uniques":0},{"timestamp":"2024-09-24T00:58:06.810Z","count":0,"uniques":0},{"timestamp":"2024-09-25T00:58:45.563Z","count":0,"uniques":0},{"timestamp":"2024-09-26T00:57:13.250Z","count":0,"uniques":0},{"timestamp":"2024-09-27T00:57:44.745Z","count":0,"uniques":0},{"timestamp":"2024-09-28T00:57:08.103Z","count":0,"uniques":0},{"timestamp":"2024-09-29T01:02:27.744Z","count":0,"uniques":0},{"timestamp":"2024-09-30T00:59:51.281Z","count":0,"uniques":0},{"timestamp":"2024-10-01T01:03:26.545Z","count":0,"uniques":0},{"timestamp":"2024-10-02T00:57:58.940Z","count":0,"uniques":0},{"timestamp":"2024-10-03T00:57:54.995Z","count":0,"uniques":0},{"timestamp":"2024-10-04T00:57:44.609Z","count":0,"uniques":0},{"timestamp":"2024-10-05T00:57:06.541Z","count":0,"uniques":0},{"timestamp":"2024-10-06T01:02:06.404Z","count":0,"uniques":0},{"timestamp":"2024-10-07T00:59:37.169Z","count":0,"uniques":0},{"timestamp":"2024-10-08T00:57:37.790Z","count":0,"uniques":0},{"timestamp":"2024-10-09T00:57:31.679Z","count":0,"uniques":0},{"timestamp":"2024-10-10T00:57:26.509Z","count":0,"uniques":0},{"timestamp":"2024-10-11T00:57:59.515Z","count":0,"uniques":0},{"timestamp":"2024-10-12T00:56:34.251Z","count":0,"uniques":0},{"timestamp":"2024-10-13T01:01:56.179Z","count":0,"uniques":0},{"timestamp":"2024-10-14T00:59:33.728Z","count":0,"uniques":0},{"timestamp":"2024-10-15T00:58:44.923Z","count":0,"uniques":0},{"timestamp":"2024-10-16T00:58:35.417Z","count":0,"uniques":0},{"timestamp":"2024-10-17T00:58:02.824Z","count":0,"uniques":0},{"timestamp":"2024-10-18T00:58:10.279Z","count":0,"uniques":0},{"timestamp":"2024-10-19T00:57:25.051Z","count":0,"uniques":0},{"timestamp":"2024-10-20T01:03:01.468Z","count":0,"uniques":0},{"timestamp":"2024-10-21T00:59:50.387Z","count":0,"uniques":0},{"timestamp":"2024-10-22T00:58:57.968Z","count":0,"uniques":0},{"timestamp":"2024-10-23T00:57:58.862Z","count":0,"uniques":0},{"timestamp":"2024-10-24T00:57:49.618Z","count":0,"uniques":0},{"timestamp":"2024-10-25T00:58:26.495Z","count":0,"uniques":0},{"timestamp":"2024-10-26T00:56:47.590Z","count":0,"uniques":0},{"timestamp":"2024-10-27T01:02:37.477Z","count":0,"uniques":0},{"timestamp":"2024-10-28T01:00:57.741Z","count":0,"uniques":0},{"timestamp":"2024-10-29T00:59:33.770Z","count":0,"uniques":0},{"timestamp":"2024-10-30T00:58:50.388Z","count":0,"uniques":0},{"timestamp":"2024-10-31T00:59:02.736Z","count":0,"uniques":0},{"timestamp":"2024-11-01T01:03:09.407Z","count":0,"uniques":0},{"timestamp":"2024-11-02T00:57:27.728Z","count":0,"uniques":0},{"timestamp":"2024-11-03T01:02:28.313Z","count":0,"uniques":0},{"timestamp":"2024-11-04T01:00:04.561Z","count":0,"uniques":0},{"timestamp":"2024-11-05T00:57:10.353Z","count":0,"uniques":0},{"timestamp":"2024-11-06T00:57:17.088Z","count":0,"uniques":0},{"timestamp":"2024-11-07T00:57:23.655Z","count":0,"uniques":0},{"timestamp":"2024-11-08T00:57:15.731Z","count":0,"uniques":0},{"timestamp":"2024-11-09T00:00:00.000Z","count":4,"uniques":1},{"timestamp":"2024-11-10T01:01:10.127Z","count":0,"uniques":0},{"timestamp":"2024-11-11T00:58:39.049Z","count":0,"uniques":0},{"timestamp":"2024-11-12T00:56:47.180Z","count":0,"uniques":0},{"timestamp":"2024-11-13T00:58:01.822Z","count":0,"uniques":0},{"timestamp":"2024-11-14T00:57:58.223Z","count":0,"uniques":0},{"timestamp":"2024-11-15T01:01:51.194Z","count":0,"uniques":0},{"timestamp":"2024-11-16T01:00:21.229Z","count":0,"uniques":0},{"timestamp":"2024-11-17T01:04:31.305Z","count":0,"uniques":0},{"timestamp":"2024-11-18T01:02:49.255Z","count":0,"uniques":0},{"timestamp":"2024-11-19T01:01:06.110Z","count":0,"uniques":0},{"timestamp":"2024-11-20T01:00:41.618Z","count":0,"uniques":0},{"timestamp":"2024-11-21T01:00:41.393Z","count":0,"uniques":0},{"timestamp":"2024-11-22T01:01:43.474Z","count":0,"uniques":0},{"timestamp":"2024-11-23T00:59:05.046Z","count":0,"uniques":0},{"timestamp":"2024-11-24T01:05:13.344Z","count":0,"uniques":0},{"timestamp":"2024-11-25T01:02:23.634Z","count":0,"uniques":0},{"timestamp":"2024-11-26T01:01:37.188Z","count":0,"uniques":0},{"timestamp":"2024-11-27T01:02:29.156Z","count":0,"uniques":0},{"timestamp":"2024-11-28T01:02:14.856Z","count":0,"uniques":0},{"timestamp":"2024-11-29T01:02:22.631Z","count":0,"uniques":0},{"timestamp":"2024-11-30T01:00:49.964Z","count":0,"uniques":0},{"timestamp":"2024-12-01T01:13:09.399Z","count":0,"uniques":0},{"timestamp":"2024-12-02T01:04:41.041Z","count":0,"uniques":0},{"timestamp":"2024-12-03T01:03:38.842Z","count":0,"uniques":0},{"timestamp":"2024-12-04T01:03:59.821Z","count":0,"uniques":0},{"timestamp":"2024-12-05T01:04:00.406Z","count":0,"uniques":0},{"timestamp":"2024-12-06T01:03:07.090Z","count":0,"uniques":0},{"timestamp":"2024-12-07T01:02:34.851Z","count":0,"uniques":0},{"timestamp":"2024-12-08T01:08:43.579Z","count":0,"uniques":0},{"timestamp":"2024-12-09T01:05:26.487Z","count":0,"uniques":0},{"timestamp":"2024-12-10T00:00:00.000Z","count":1,"uniques":1},{"timestamp":"2024-12-11T01:03:37.422Z","count":0,"uniques":0},{"timestamp":"2024-12-12T01:03:30.050Z","count":0,"uniques":0},{"timestamp":"2024-12-13T01:04:37.596Z","count":0,"uniques":0},{"timestamp":"2024-12-14T01:01:41.427Z","count":0,"uniques":0},{"timestamp":"2024-12-15T01:08:27.802Z","count":0,"uniques":0},{"timestamp":"2024-12-16T01:05:51.528Z","count":0,"uniques":0},{"timestamp":"2024-12-17T01:03:47.428Z","count":0,"uniques":0},{"timestamp":"2024-12-18T01:00:55.738Z","count":0,"uniques":0},{"timestamp":"2024-12-19T01:01:34.772Z","count":0,"uniques":0},{"timestamp":"2024-12-20T00:58:37.679Z","count":0,"uniques":0},{"timestamp":"2024-12-21T00:57:28.751Z","count":0,"uniques":0},{"timestamp":"2024-12-22T00:00:00.000Z","count":2,"uniques":1},{"timestamp":"2024-12-23T00:59:52.271Z","count":0,"uniques":0},{"timestamp":"2024-12-24T00:58:34.893Z","count":0,"uniques":0},{"timestamp":"2024-12-25T00:57:53.212Z","count":0,"uniques":0},{"timestamp":"2024-12-26T00:57:52.643Z","count":0,"uniques":0},{"timestamp":"2024-12-27T00:58:24.623Z","count":0,"uniques":0},{"timestamp":"2024-12-28T00:57:18.683Z","count":0,"uniques":0},{"timestamp":"2024-12-29T01:03:58.815Z","count":0,"uniques":0},{"timestamp":"2024-12-30T01:00:34.429Z","count":0,"uniques":0},{"timestamp":"2024-12-31T00:58:08.884Z","count":0,"uniques":0},{"timestamp":"2025-01-01T01:03:29.455Z","count":0,"uniques":0},{"timestamp":"2025-01-02T00:58:00.422Z","count":0,"uniques":0},{"timestamp":"2025-01-03T00:58:33.249Z","count":0,"uniques":0},{"timestamp":"2025-01-04T00:57:25.192Z","count":0,"uniques":0},{"timestamp":"2025-01-05T01:03:21.731Z","count":0,"uniques":0},{"timestamp":"2025-01-06T01:01:16.036Z","count":0,"uniques":0},{"timestamp":"2025-01-07T00:58:54.662Z","count":0,"uniques":0},{"timestamp":"2025-01-08T00:58:44.210Z","count":0,"uniques":0},{"timestamp":"2025-01-09T00:58:24.896Z","count":0,"uniques":0},{"timestamp":"2025-01-10T01:00:15.667Z","count":0,"uniques":0},{"timestamp":"2025-01-11T00:59:08.735Z","count":0,"uniques":0},{"timestamp":"2025-01-12T01:04:13.759Z","count":0,"uniques":0},{"timestamp":"2025-01-13T01:02:07.173Z","count":0,"uniques":0},{"timestamp":"2025-01-14T00:56:12.669Z","count":0,"uniques":0},{"timestamp":"2025-01-15T00:57:34.778Z","count":0,"uniques":0},{"timestamp":"2025-01-16T00:56:46.851Z","count":0,"uniques":0},{"timestamp":"2025-01-17T00:56:43.001Z","count":0,"uniques":0},{"timestamp":"2025-01-18T00:55:06.263Z","count":0,"uniques":0},{"timestamp":"2025-01-19T01:01:29.689Z","count":0,"uniques":0},{"timestamp":"2025-01-20T00:57:57.530Z","count":0,"uniques":0},{"timestamp":"2025-01-21T00:56:56.870Z","count":0,"uniques":0},{"timestamp":"2025-01-22T00:58:34.258Z","count":0,"uniques":0},{"timestamp":"2025-01-23T00:57:13.340Z","count":0,"uniques":0},{"timestamp":"2025-01-24T00:57:22.516Z","count":0,"uniques":0},{"timestamp":"2025-01-25T00:54:10.462Z","count":0,"uniques":0},{"timestamp":"2025-01-26T00:58:56.426Z","count":0,"uniques":0},{"timestamp":"2025-01-27T00:58:19.309Z","count":0,"uniques":0},{"timestamp":"2025-01-28T00:57:11.870Z","count":0,"uniques":0},{"timestamp":"2025-01-29T00:57:06.543Z","count":0,"uniques":0},{"timestamp":"2025-01-30T00:56:29.180Z","count":0,"uniques":0},{"timestamp":"2025-01-31T00:57:33.501Z","count":0,"uniques":0},{"timestamp":"2025-02-01T01:00:35.367Z","count":0,"uniques":0},{"timestamp":"2025-02-02T01:00:09.666Z","count":0,"uniques":0},{"timestamp":"2025-02-03T00:58:22.374Z","count":0,"uniques":0},{"timestamp":"2025-02-04T00:57:29.647Z","count":0,"uniques":0},{"timestamp":"2025-02-05T00:58:04.928Z","count":0,"uniques":0},{"timestamp":"2025-02-06T00:58:18.465Z","count":0,"uniques":0},{"timestamp":"2025-02-07T00:58:32.829Z","count":0,"uniques":0},{"timestamp":"2025-02-08T00:57:02.743Z","count":0,"uniques":0},{"timestamp":"2025-02-09T01:01:16.971Z","count":0,"uniques":0},{"timestamp":"2025-02-10T00:59:07.800Z","count":0,"uniques":0},{"timestamp":"2025-02-11T00:58:07.577Z","count":0,"uniques":0},{"timestamp":"2025-02-12T00:58:32.171Z","count":0,"uniques":0},{"timestamp":"2025-02-13T00:58:37.007Z","count":0,"uniques":0},{"timestamp":"2025-02-14T00:58:22.385Z","count":0,"uniques":0},{"timestamp":"2025-02-15T00:57:41.667Z","count":0,"uniques":0},{"timestamp":"2025-02-16T01:03:12.760Z","count":0,"uniques":0},{"timestamp":"2025-02-17T01:00:52.322Z","count":0,"uniques":0},{"timestamp":"2025-02-18T00:58:01.196Z","count":0,"uniques":0},{"timestamp":"2025-02-19T00:58:38.881Z","count":0,"uniques":0},{"timestamp":"2025-02-20T00:59:00.438Z","count":0,"uniques":0},{"timestamp":"2025-02-21T00:58:57.522Z","count":0,"uniques":0},{"timestamp":"2025-02-22T00:57:19.592Z","count":0,"uniques":0},{"timestamp":"2025-02-23T01:03:17.862Z","count":0,"uniques":0},{"timestamp":"2025-02-24T01:00:46.401Z","count":0,"uniques":0},{"timestamp":"2025-02-25T00:59:59.297Z","count":0,"uniques":0},{"timestamp":"2025-02-26T01:00:00.642Z","count":0,"uniques":0},{"timestamp":"2025-02-27T00:59:47.207Z","count":0,"uniques":0},{"timestamp":"2025-02-28T01:00:13.493Z","count":0,"uniques":0},{"timestamp":"2025-03-01T01:04:28.545Z","count":0,"uniques":0},{"timestamp":"2025-03-02T01:03:40.770Z","count":0,"uniques":0},{"timestamp":"2025-03-03T01:02:01.345Z","count":0,"uniques":0},{"timestamp":"2025-03-04T01:01:01.070Z","count":0,"uniques":0},{"timestamp":"2025-03-05T01:00:53.404Z","count":0,"uniques":0},{"timestamp":"2025-03-06T01:00:53.529Z","count":0,"uniques":0},{"timestamp":"2025-03-07T01:01:45.884Z","count":0,"uniques":0},{"timestamp":"2025-03-08T00:48:09.532Z","count":0,"uniques":0},{"timestamp":"2025-03-09T00:53:28.860Z","count":0,"uniques":0},{"timestamp":"2025-03-10T00:52:20.197Z","count":0,"uniques":0},{"timestamp":"2025-03-11T01:01:33.738Z","count":0,"uniques":0},{"timestamp":"2025-03-12T01:00:49.383Z","count":0,"uniques":0},{"timestamp":"2025-03-13T01:01:49.092Z","count":0,"uniques":0},{"timestamp":"2025-03-14T01:00:59.217Z","count":0,"uniques":0},{"timestamp":"2025-03-15T01:00:11.716Z","count":0,"uniques":0},{"timestamp":"2025-03-16T01:06:07.900Z","count":0,"uniques":0},{"timestamp":"2025-03-17T01:03:36.225Z","count":0,"uniques":0},{"timestamp":"2025-03-18T01:01:46.804Z","count":0,"uniques":0},{"timestamp":"2025-03-19T01:02:16.212Z","count":0,"uniques":0},{"timestamp":"2025-03-20T01:01:23.634Z","count":0,"uniques":0},{"timestamp":"2025-03-21T01:02:46.828Z","count":0,"uniques":0},{"timestamp":"2025-03-22T01:00:32.401Z","count":0,"uniques":0},{"timestamp":"2025-03-23T01:06:25.815Z","count":0,"uniques":0},{"timestamp":"2025-03-24T01:04:14.009Z","count":0,"uniques":0},{"timestamp":"2025-03-25T01:02:59.050Z","count":0,"uniques":0},{"timestamp":"2025-03-26T01:02:49.045Z","count":0,"uniques":0},{"timestamp":"2025-03-27T01:02:16.338Z","count":0,"uniques":0},{"timestamp":"2025-03-28T01:02:29.290Z","count":0,"uniques":0},{"timestamp":"2025-03-29T01:02:03.331Z","count":0,"uniques":0},{"timestamp":"2025-03-30T01:07:40.691Z","count":0,"uniques":0},{"timestamp":"2025-03-31T01:06:15.762Z","count":0,"uniques":0},{"timestamp":"2025-04-01T01:10:40.809Z","count":0,"uniques":0},{"timestamp":"2025-04-02T01:03:37.889Z","count":0,"uniques":0},{"timestamp":"2025-04-03T01:03:15.806Z","count":0,"uniques":0},{"timestamp":"2025-04-04T01:02:20.105Z","count":0,"uniques":0},{"timestamp":"2025-04-05T01:01:56.511Z","count":0,"uniques":0},{"timestamp":"2025-04-06T01:07:13.898Z","count":0,"uniques":0},{"timestamp":"2025-04-07T01:05:14.000Z","count":0,"uniques":0},{"timestamp":"2025-04-08T01:03:20.969Z","count":0,"uniques":0},{"timestamp":"2025-04-09T01:03:25.784Z","count":0,"uniques":0},{"timestamp":"2025-04-10T01:03:33.175Z","count":0,"uniques":0},{"timestamp":"2025-04-11T01:03:44.383Z","count":0,"uniques":0},{"timestamp":"2025-04-12T01:02:49.248Z","count":0,"uniques":0},{"timestamp":"2025-04-13T02:32:21.044Z","count":0,"uniques":0},{"timestamp":"2025-04-14T01:06:24.658Z","count":0,"uniques":0},{"timestamp":"2025-04-15T01:05:29.479Z","count":0,"uniques":0},{"timestamp":"2025-04-16T07:34:00.835Z","count":0,"uniques":0},{"timestamp":"2025-04-17T07:34:00.835Z","count":0,"uniques":0},{"timestamp":"2025-04-18T07:34:00.835Z","count":0,"uniques":0},{"timestamp":"2025-04-19T07:34:00.835Z","count":0,"uniques":0},{"timestamp":"2025-04-20T07:34:00.835Z","count":0,"uniques":0},{"timestamp":"2025-04-21T07:34:00.835Z","count":0,"uniques":0},{"timestamp":"2025-04-22T07:34:00.835Z","count":0,"uniques":0},{"timestamp":"2025-04-23T07:34:00.835Z","count":0,"uniques":0},{"timestamp":"2025-04-24T07:34:00.835Z","count":0,"uniques":0},{"timestamp":"2025-04-25T07:34:00.835Z","count":0,"uniques":0},{"timestamp":"2025-04-26T07:34:00.835Z","count":0,"uniques":0},{"timestamp":"2025-04-27T07:34:00.835Z","count":0,"uniques":0},{"timestamp":"2025-04-28T07:34:00.835Z","count":0,"uniques":0},{"timestamp":"2025-04-29T07:34:00.835Z","count":0,"uniques":0},{"timestamp":"2025-04-30T07:34:00.835Z","count":0,"uniques":0},{"timestamp":"2025-05-01T01:11:36.915Z","count":0,"uniques":0},{"timestamp":"2025-05-02T01:05:55.028Z","count":0,"uniques":0},{"timestamp":"2025-05-03T01:04:20.256Z","count":0,"uniques":0},{"timestamp":"2025-05-04T01:12:25.864Z","count":0,"uniques":0},{"timestamp":"2025-05-05T01:09:04.113Z","count":0,"uniques":0},{"timestamp":"2025-05-06T01:06:19.927Z","count":0,"uniques":0},{"timestamp":"2025-05-07T01:06:43.795Z","count":0,"uniques":0},{"timestamp":"2025-05-08T01:07:05.085Z","count":0,"uniques":0},{"timestamp":"2025-05-09T01:06:35.155Z","count":0,"uniques":0},{"timestamp":"2025-05-10T01:04:14.741Z","count":0,"uniques":0},{"timestamp":"2025-05-11T01:11:09.906Z","count":0,"uniques":0},{"timestamp":"2025-05-12T01:09:30.516Z","count":0,"uniques":0},{"timestamp":"2025-05-13T01:07:54.002Z","count":0,"uniques":0},{"timestamp":"2025-05-14T01:06:43.539Z","count":0,"uniques":0},{"timestamp":"2025-05-15T01:04:25.256Z","count":0,"uniques":0},{"timestamp":"2025-05-16T01:07:55.820Z","count":0,"uniques":0},{"timestamp":"2025-05-17T01:06:19.092Z","count":0,"uniques":0},{"timestamp":"2025-05-18T01:11:53.763Z","count":0,"uniques":0},{"timestamp":"2025-05-19T01:10:35.373Z","count":0,"uniques":0},{"timestamp":"2025-05-20T01:08:27.648Z","count":0,"uniques":0},{"timestamp":"2025-05-21T01:07:58.818Z","count":0,"uniques":0},{"timestamp":"2025-05-22T01:07:26.399Z","count":0,"uniques":0},{"timestamp":"2025-05-23T01:07:19.724Z","count":0,"uniques":0},{"timestamp":"2025-05-24T01:04:56.748Z","count":0,"uniques":0},{"timestamp":"2025-05-25T01:13:40.314Z","count":0,"uniques":0},{"timestamp":"2025-05-26T01:09:32.719Z","count":0,"uniques":0},{"timestamp":"2025-05-27T01:06:48.243Z","count":0,"uniques":0},{"timestamp":"2025-05-28T01:08:12.055Z","count":0,"uniques":0},{"timestamp":"2025-05-29T01:08:17.650Z","count":0,"uniques":0},{"timestamp":"2025-05-30T01:06:15.993Z","count":0,"uniques":0},{"timestamp":"2025-05-31T01:06:23.026Z","count":0,"uniques":0},{"timestamp":"2025-06-01T01:20:43.926Z","count":0,"uniques":0},{"timestamp":"2025-06-02T01:11:13.434Z","count":0,"uniques":0}]
